d2draftnet/__init__.py
d2draftnet/collect_data1.py
d2draftnet/collect_data_old.py
d2draftnet/collect_match_ids.py
d2draftnet/config.py
d2draftnet/embedding_model.py
d2draftnet/models/7_37e_model.pth
d2draftnet/odds_calculator.py
d2draftnet/predict_embedding_model.py
d2draftnet/train_embedding_model.py
d2draftnet-0.1.3.dist-info/METADATA
d2draftnet-0.1.3.dist-info/WHEEL
d2draftnet-0.1.3.dist-info/RECORD
