Metadata-Version: 2.3
Name: d2draftnet
Version: 0.1.3
Summary: 
Author: gkerr708
Author-email: gkerr708@gmail.com
Requires-Python: >=3.10
Classifier: Programming Language :: Python :: 3
Classifier: Programming Language :: Python :: 3.10
Classifier: Programming Language :: Python :: 3.11
Classifier: Programming Language :: Python :: 3.12
Classifier: Programming Language :: Python :: 3.13
Requires-Dist: beautifulsoup4 (>=4.13.3,<5.0.0)
Requires-Dist: click (>=8.1.8,<9.0.0)
Requires-Dist: fastparquet (>=2024.11.0,<2025.0.0)
Requires-Dist: pandas (>=2.2.3,<3.0.0)
Requires-Dist: pyarrow (>=19.0.1,<20.0.0)
Requires-Dist: torch (>=2.6.0,<3.0.0)
